{
    "vnetName": {
        "value": "test-vnet-1"
    },
    "subnetName": {
        "value": "test-sn-1"
    },
    "subnetPrefix": {
        "value": "10.0.1.0/24"
    },
    "nsgName": {
        "value": "test-nsg"
    },
    "numberOfWindowsVMs": {
        "value": 1
    },
    "numberOfLinuxVMs": {
        "value": 1
    },
    "vmSize": {
        "value": "Standard_B1ls"
    },
    "windowsAdminUsername": {
        "value": "felixyh"
    },
    "windowsAdminPassword": {
        "value": "P@ssw0rd201017"
    },
    "linuxAdminUsername": {
        "value": "felixyh"
    },
    "linuxAdminPassword": {
        "value": "P@ssword200117"
    },
    "sshSourceIPAddresses": {
        "value": [
            "4.71.171.82"
        ]
    },
    "rdpSourceIPAddresses": {
        "value": [
            "4.71.171.82"
        ]
    },
    "authenticationType": {
        "value": "password"
    }
}